graphvision/__init__.py
graphvision/segment.py
graphvision-0.1.3.dist-info/LICENSE
graphvision-0.1.3.dist-info/METADATA
graphvision-0.1.3.dist-info/WHEEL
graphvision-0.1.3.dist-info/top_level.txt
graphvision-0.1.3.dist-info/RECORD
