Metadata-Version: 2.1
Name: graphvision
Version: 0.1.3
Summary: Create topological graph for image segments
Home-page: UNKNOWN
Author: mishra-18
Author-email: mishra4475@gmail.com
License: MIT
Platform: UNKNOWN
Classifier: Programming Language :: Python :: 3
Classifier: License :: OSI Approved :: MIT License
Classifier: Operating System :: OS Independent
License-File: LICENSE
Requires-Dist: huggingface-hub
Requires-Dist: matplotlib >=3.5.1
Requires-Dist: networkx >=2.7
Requires-Dist: numpy >=1.22.0
Requires-Dist: opencv-python >=4.5
Requires-Dist: pillow >=9.0.1
Requires-Dist: segment-anything
Requires-Dist: torch >=1.2.0
Requires-Dist: torch-geometric >=2.0.4
Requires-Dist: transformers >=4.36.2
